__init__.py
context.py
utils.py
mseep_qmt_mcp_server-0.1.6.dist-info/METADATA
mseep_qmt_mcp_server-0.1.6.dist-info/WHEEL
mseep_qmt_mcp_server-0.1.6.dist-info/top_level.txt
mseep_qmt_mcp_server-0.1.6.dist-info/RECORD
